src/__init__.py
src/cli.py
src/cron.py
src/executor.py
jplan-1.1.0.dist-info/METADATA
jplan-1.1.0.dist-info/WHEEL
jplan-1.1.0.dist-info/entry_points.txt
jplan-1.1.0.dist-info/RECORD
