Metadata-Version: 2.4
Name: jplan
Version: 1.1.0
Summary: A command-line tool to schedule and execute Jupyter notebooks using cron
Project-URL: Homepage, https://github.com/apoplexi24/jplan
Project-URL: Documentation, https://github.com/apoplexi24/jplan#readme
Project-URL: Repository, https://github.com/apoplexi24/jplan.git
Project-URL: Issues, https://github.com/apoplexi24/jplan/issues
Author-email: apoplexi24 <shivanandanasharma@gmail.com>
License-Expression: MIT
Keywords: cron,jupyter,notebook,papermill,scheduling
Classifier: Development Status :: 3 - Alpha
Classifier: Intended Audience :: Developers
Classifier: License :: OSI Approved :: MIT License
Classifier: Programming Language :: Python :: 3
Classifier: Programming Language :: Python :: 3.8
Classifier: Programming Language :: Python :: 3.9
Classifier: Programming Language :: Python :: 3.10
Classifier: Programming Language :: Python :: 3.11
Classifier: Programming Language :: Python :: 3.12
Classifier: Programming Language :: Python :: 3.13
Classifier: Programming Language :: Python :: 3.14
Requires-Python: >=3.8
Requires-Dist: jupyter>=1.0.0
Requires-Dist: papermill>=2.4.0
Provides-Extra: dev
Requires-Dist: black>=23.0.0; extra == 'dev'
Requires-Dist: isort>=5.0.0; extra == 'dev'
Requires-Dist: pytest>=7.0.0; extra == 'dev'
